sdss_access/__init__.py
sdss_access/etc/sdss_access.yml
sdss_access/misc/__init__.py
sdss_access/misc/docupaths.py
sdss_access/path/__init__.py
sdss_access/path/changelog.py
sdss_access/path/path.py
sdss_access/sync/__init__.py
sdss_access/sync/access.py
sdss_access/sync/auth.py
sdss_access/sync/baseaccess.py
sdss_access/sync/cli.py
sdss_access/sync/curl.py
sdss_access/sync/http.py
sdss_access/sync/rsync.py
sdss_access/sync/stream.py
sdss_access/sync/system_call.py
sdss_access-3.0.10.dist-info/licenses/LICENSE.md
sdss_access-3.0.10.dist-info/METADATA
sdss_access-3.0.10.dist-info/WHEEL
sdss_access-3.0.10.dist-info/top_level.txt
sdss_access-3.0.10.dist-info/RECORD
